pyqsp/LPoly.py
pyqsp/__init__.py
pyqsp/angle_sequence.py
pyqsp/completion.py
pyqsp/decomposition.py
pyqsp/ham_sim.py
pyqsp/main.py
pyqsp/phases.py
pyqsp/poly.py
pyqsp/response.py
pyqsp/qsp_models/__init__.py
pyqsp/qsp_models/qsp_circuit.py
pyqsp/qsp_models/qsp_layers.py
pyqsp/qsp_models/tfq_qsp_layers.py
pyqsp/qsp_models/viz_tools.py
pyqsp/test/__init__.py
pyqsp/test/test_angle_sequence.py
pyqsp/test/test_completion.py
pyqsp/test/test_lpoly.py
pyqsp/test/test_main.py
pyqsp/test/test_poly.py
pyqsp/test/test_qsp_models.py
pyqsp/test/test_response.py
pyqsp-0.1.4.dist-info/LICENSE
pyqsp-0.1.4.dist-info/METADATA
pyqsp-0.1.4.dist-info/WHEEL
pyqsp-0.1.4.dist-info/entry_points.txt
pyqsp-0.1.4.dist-info/top_level.txt
pyqsp-0.1.4.dist-info/RECORD
