Metadata-Version: 2.1
Name: pyqsp
Version: 0.1.4
Summary: Generate phase angles for quantum signal processing algorithms
Home-page: https://github.com/ichuang/pyqsp
Author: I. Chuang, J. Docter, J.M. Martyn, Z. Rossi, A. Tan
Author-email: ichuang@mit.edu
License: LICENSE.txt
Platform: UNKNOWN
Requires-Dist: matplotlib
Requires-Dist: numpy (~=1.19.2)
Requires-Dist: scipy
